datasci_stdlib_tools-1.0.1.dist-info/DESCRIPTION.rst
datasci_stdlib_tools-1.0.1.dist-info/METADATA
datasci_stdlib_tools-1.0.1.dist-info/RECORD
datasci_stdlib_tools-1.0.1.dist-info/WHEEL
datasci_stdlib_tools-1.0.1.dist-info/metadata.json
datasci_stdlib_tools-1.0.1.dist-info/top_level.txt
datasci_tools/__init__.py
datasci_tools/abstract_class_utils.py
datasci_tools/algorithms_utils.py
datasci_tools/argparse_utils.py
datasci_tools/data_struct_utils.py
datasci_tools/dataclass_utils.py
datasci_tools/datajoint_motifs.py
datasci_tools/dict_utils.py
datasci_tools/dj_utils.py
datasci_tools/docstring_utils.py
datasci_tools/dotmotif_utils.py
datasci_tools/enum_utils.py
datasci_tools/file_utils.py
datasci_tools/filtering_utils.py
datasci_tools/function_utils.py
datasci_tools/general_utils.py
datasci_tools/hash_utils.py
datasci_tools/inspect_utils.py
datasci_tools/ipyvolume_movie_utils.py
datasci_tools/ipyvolume_utils.py
datasci_tools/json_utils.py
datasci_tools/linalg_utils.py
datasci_tools/logging_utils.py
datasci_tools/matlab_utils.py
datasci_tools/matplotlib_utils.py
datasci_tools/mesh_utils.py
datasci_tools/module_utils.py
datasci_tools/networkx_utils.py
datasci_tools/new_module.py
datasci_tools/numpy_dep.py
datasci_tools/numpy_utils.py
datasci_tools/object_oriented_utils.py
datasci_tools/package_utils.py
datasci_tools/pandas_utils.py
datasci_tools/pathlib_utils.py
datasci_tools/pipeline.py
datasci_tools/pretty_print_confusion_matrix.py
datasci_tools/pydantic_utls.py
datasci_tools/regex_utils.py
datasci_tools/requirement_utils.py
datasci_tools/scipy_utils.py
datasci_tools/seaborn_utils.py
datasci_tools/setup_py_utils.py
datasci_tools/statistics_utils.py
datasci_tools/statistics_visualizations.py
datasci_tools/string_utils.py
datasci_tools/system_utils.py
datasci_tools/tqdm_utils.py
datasci_tools/typeing_utils.py
datasci_tools/widget_utils.py
