Metadata-Version: 2.0
Name: datasci-stdlib-tools
Version: 1.0.1
Summary: Utility functions for commonly used data science packages (numpy, pandas, etc) and generic python utility functions
Home-page: UNKNOWN
Author: Brendan Celii
Author-email: brendanacelii@gmail.com
License: UNKNOWN
Project-URL: Source, https://github.com/reimerlab/datasci_tools
Project-URL: Documentation, https://reimerlab.github.io/datasci_tools/
Platform: UNKNOWN
Requires-Dist: numpy (>=1.19.5)
Requires-Dist: pykdtree (>=1.3.1)
Requires-Dist: pandas (>=1.1.5)
Requires-Dist: colour (>=0.1.5)
Requires-Dist: ipython
Requires-Dist: ipyvolume (>=0.5.2)
Requires-Dist: ipywebrtc (>=0.5.0)
Requires-Dist: ipywidgets (>=7.5.1)
Requires-Dist: matplotlib (>=3.3.4)
Requires-Dist: modin (>=0.8.3.post4)
Requires-Dist: networkx (>=2.5)
Requires-Dist: pandasql (>=0.7.3)
Requires-Dist: pydantic (>=1.9.2)
Requires-Dist: pydot (>=1.4.2)
Requires-Dist: regex (>=2023.6.3)
Requires-Dist: scikit-learn
Requires-Dist: scipy (>=1.5.4)
Requires-Dist: seaborn (>=0.11.2)
Requires-Dist: setuptools (>=39.0.1)
Requires-Dist: Shapely (>=1.7.0)
Requires-Dist: six (>=1.11.0)
Requires-Dist: tqdm (>=4.62.2)
Requires-Dist: trimesh (>=3.9.0)
Requires-Dist: webcolors (>=1.11.1)
Requires-Dist: ipython-genutils
